README.rst
setup.py
bin/pgv
pgv/__init__.py
pgv/collector.py
pgv/config.py
pgv/format.py
pgv/initializer.py
pgv/installer.py
pgv/loader.py
pgv/package.py
pgv/skiplist.py
pgv/tracker.py
pgv/vcs.py
pgv/viewer.py
pgv.egg-info/PKG-INFO
pgv.egg-info/SOURCES.txt
pgv.egg-info/dependency_links.txt
pgv.egg-info/requires.txt
pgv.egg-info/top_level.txt
pgv/data/init.sql
pgv/utils/__init__.py
pgv/utils/app.py
pgv/utils/exceptions.py
pgv/utils/misc.py
pgv/utils/options.py
pgv/vcs_provider/__init__.py
pgv/vcs_provider/git_vcs.py