Metadata-Version: 1.1
Name: pgv
Version: 0.0.2
Summary: PostgreSQL schema versioning tool
Home-page: https://github.com/go1dshtein/pgv
Author: Kirill Goldshtein
Author-email: goldshtein.kirill@gmail.com
License: GPLv2
Platform: UNKNOWN
Classifier: Intended Audience :: Developers
Classifier: Environment :: Console
Classifier: Programming Language :: Python :: 2.7
Classifier: Natural Language :: English
Classifier: Development Status :: 1 - Planning
Classifier: Operating System :: Unix
Classifier: Topic :: Utilities
